README.rst
setup.py
messaging/__init__.py
messaging/utils.py
messaging/mms/__init__.py
messaging/mms/iterator.py
messaging/mms/message.py
messaging/mms/mms_pdu.py
messaging/mms/wsp_pdu.py
messaging/sms/__init__.py
messaging/sms/base.py
messaging/sms/consts.py
messaging/sms/deliver.py
messaging/sms/gsm0338.py
messaging/sms/pdu.py
messaging/sms/submit.py
messaging/sms/udh.py
messaging/sms/wap.py
python_messaging.egg-info/PKG-INFO
python_messaging.egg-info/SOURCES.txt
python_messaging.egg-info/dependency_links.txt
python_messaging.egg-info/not-zip-safe
python_messaging.egg-info/top_level.txt