Metadata-Version: 1.1
Name: python-messaging
Version: 0.5.13
Summary: SMS and MMS message encoder/decoder.
Home-page: UNKNOWN
Author: UNKNOWN
Author-email: UNKNOWN
License: GNU GENERAL PUBLIC LICENSE Version 2, June 1991
Platform: UNKNOWN
Classifier: Development Status :: 5 - Production/Stable
Classifier: License :: OSI Approved :: GNU General Public License (GPL)
Classifier: Natural Language :: English
Classifier: Operating System :: POSIX :: Linux
Classifier: Programming Language :: Python
Classifier: Programming Language :: Python :: 3
Classifier: Programming Language :: Python :: 3.5
Classifier: Programming Language :: Python :: 3.6
Classifier: Programming Language :: Python :: 3.7
Classifier: Programming Language :: Python :: 3.8
Classifier: Topic :: Communications :: Telephony
